<?xml version="1.0" encoding="UTF-8"?>
<VYSLEDKY_OKRSKY xmlns="http://www.volby.cz/prezident/" xmlns:xsi="http://www.w3.org/2001/XMLSchema-instance"
                 xsi:schemaLocation="http://www.volby.cz/prezident/ pe_vysledky_okrsky.xsd"
                 DATUM_CAS_GENEROVANI="2023-01-14T14:20:00">
<DAVKA KOLO="1" PORADI_DAVKY="1" OKRSKY_DAVKA="2" OKRSKY_CELKEM="14857" OKRSKY_ZPRAC="2"/>
<OKRSEK CIS_OBEC="577731" CIS_OKRSEK="18" PORADI_ZPRAC="1" DATUM_CAS_ZPRAC="2023-01-14T14:19:11" OPAKOVANE="0">
<UCAST_OKRSEK ZAPSANI_VOLICI="554" VYDANE_OBALKY="56" ODEVZDANE_OBALKY="56" PLATNE_HLASY="56"/>
<HLASY_OKRSEK PORADOVE_CISLO="1" HLASY="2"/>
<HLASY_OKRSEK PORADOVE_CISLO="2" HLASY="1"/>
<HLASY_OKRSEK PORADOVE_CISLO="4" HLASY="17"/>
<HLASY_OKRSEK PORADOVE_CISLO="6" HLASY="10"/>
<HLASY_OKRSEK PORADOVE_CISLO="7" HLASY="22"/>
<HLASY_OKRSEK PORADOVE_CISLO="9" HLASY="4"/>
</OKRSEK>
<OKRSEK CIS_OBEC="566101" CIS_OKRSEK="1" PORADI_ZPRAC="2" DATUM_CAS_ZPRAC="2023-01-14T14:19:22" OPAKOVANE="0">
<UCAST_OKRSEK ZAPSANI_VOLICI="68" VYDANE_OBALKY="59" ODEVZDANE_OBALKY="59" PLATNE_HLASY="59"/>
<HLASY_OKRSEK PORADOVE_CISLO="1" HLASY="2"/>
<HLASY_OKRSEK PORADOVE_CISLO="2" HLASY="6"/>
<HLASY_OKRSEK PORADOVE_CISLO="4" HLASY="10"/>
<HLASY_OKRSEK PORADOVE_CISLO="6" HLASY="7"/>
<HLASY_OKRSEK PORADOVE_CISLO="7" HLASY="32"/>
<HLASY_OKRSEK PORADOVE_CISLO="9" HLASY="2"/>
</OKRSEK>
</VYSLEDKY_OKRSKY>
